dictlogic/__init__.py
dictlogic/builtins.py
dictlogic/logic.py
dictlogic/scope.py
dictlogic/types.py
dictlogic/utils.py
dict_logic-1.0.2.dist-info/METADATA
dict_logic-1.0.2.dist-info/WHEEL
dict_logic-1.0.2.dist-info/top_level.txt
dict_logic-1.0.2.dist-info/RECORD
