Metadata-Version: 2.1
Name: dict-logic
Version: 1.0.2
Summary: UNKNOWN
Home-page: https://github.com/jonghwanhyeon/dict-logic
Author: Jonghwan Hyeon
Author-email: hyeon0145@gmail.com
License: UNKNOWN
Keywords: dict logic
Platform: UNKNOWN
Classifier: Development Status :: 4 - Beta
Classifier: Intended Audience :: Developers
Classifier: License :: OSI Approved :: MIT License
Classifier: Programming Language :: Python :: 3
Classifier: Programming Language :: Python :: 3 :: Only
